<?xml version="1.0" encoding="utf-8" ?>
<dwsync>
<file name="background.png" server="190.14.52.148//cl/abreme/api/" local="131249834230208745" remote="130970412000000000" Dst="2" />
<file name="motor.png" server="190.14.52.148//cl/abreme/api/" local="131249834236440188" remote="130970412000000000" Dst="2" />
<file name="sofa-3a4c8b.jpg" server="190.14.52.148//cl/abreme/api/" local="131249834237210129" remote="130970412000000000" Dst="2" />
<file name="sofa-746153.jpg" server="190.14.52.148//cl/abreme/api/" local="131249834238144154" remote="130970412000000000" Dst="2" />
<file name="sofa-ac120f.jpg" server="190.14.52.148//cl/abreme/api/" local="131249834238909673" remote="130970412000000000" Dst="2" />
<file name="interior-bg.png" server="190.14.52.148//cl/abreme/api/" local="131249834238929696" remote="130970412000000000" Dst="2" />
<file name="sofa-d2d2d2.jpg" server="190.14.52.148//cl/abreme/api/" local="131249834239370004" remote="130970412000000000" Dst="2" />
<file name="sofa-ddd1c3.jpg" server="190.14.52.148//cl/abreme/api/" local="131249834239425046" remote="130970412000000000" Dst="2" />
<file name="sofa-fb455f.jpg" server="190.14.52.148//cl/abreme/api/" local="131249834239850369" remote="130970412000000000" Dst="2" />
<file name="sofa-ffcc33.jpg" server="190.14.52.148//cl/abreme/api/" local="131249834240050488" remote="130970412000000000" Dst="2" />
</dwsync>