<?xml version="1.0" encoding="utf-8" ?>
<dwsync>
<file name="angular.html" server="190.14.52.148//cl/abreme/api/" local="131249834448719421" remote="130970412000000000" Dst="2" />
<file name="api.html" server="190.14.52.148//cl/abreme/api/" local="131249834449104702" remote="130970412000000000" Dst="2" />
<file name="column-resizing.html" server="190.14.52.148//cl/abreme/api/" local="131249834449324858" remote="130970412000000000" Dst="2" />
<file name="events.html" server="190.14.52.148//cl/abreme/api/" local="131249834450105403" remote="130970412000000000" Dst="2" />
<file name="index.html" server="190.14.52.148//cl/abreme/api/" local="131249834450320596" remote="130970412000000000" Dst="2" />
<file name="keyboard-navigation.html" server="190.14.52.148//cl/abreme/api/" local="131249834450825925" remote="130970412000000000" Dst="2" />
<file name="mvvm.html" server="190.14.52.148//cl/abreme/api/" local="131249834451421359" remote="130970412000000000" Dst="2" />
<file name="resources.html" server="190.14.52.148//cl/abreme/api/" local="131249834451636491" remote="130970412000000000" Dst="2" />
<file name="right-to-left-support.html" server="190.14.52.148//cl/abreme/api/" local="131249834451836643" remote="130970412000000000" Dst="2" />
<file name="task-template.html" server="190.14.52.148//cl/abreme/api/" local="131249834452902398" remote="130970412000000000" Dst="2" />
</dwsync>